shutyl/__about__.py
shutyl/__init__.py
shutyl/config.py
shutyl/file_sync.py
shutyl/main.py
shutyl/signal_monitor.py
shutyl-0.0.5.dist-info/METADATA
shutyl-0.0.5.dist-info/WHEEL
shutyl-0.0.5.dist-info/entry_points.txt
shutyl-0.0.5.dist-info/licenses/LICENSE.txt
shutyl-0.0.5.dist-info/RECORD
